rel/__init__.py
rel/buff.py
rel/errors.py
rel/listener.py
rel/registrar.py
rel/rel.py
rel/test.py
rel/tools.py
rel/util.py
rel/version.py
rel-0.4.9.21.dist-info/LICENSE
rel-0.4.9.21.dist-info/METADATA
rel-0.4.9.21.dist-info/WHEEL
rel-0.4.9.21.dist-info/entry_points.txt
rel-0.4.9.21.dist-info/top_level.txt
rel-0.4.9.21.dist-info/RECORD
