Metadata-Version: 2.1
Name: rel
Version: 0.4.9.21
Summary: Registered Event Listener. Provides standard (pyevent) interface and functionality without external dependencies
Author: Mario Balibrera
Author-email: mario.balibrera@gmail.com
License: MIT License
Classifier: Development Status :: 5 - Production/Stable
Classifier: Environment :: Console
Classifier: Intended Audience :: Developers
Classifier: License :: OSI Approved :: MIT License
Classifier: Operating System :: OS Independent
Classifier: Programming Language :: Python
Classifier: Topic :: Software Development :: Libraries :: Python Modules
License-File: LICENSE
